customer_segmentation/__init__.py
customer_segmentation/customer_segmentation.py
customer_segmentation-0.0.1.dist-info/WHEEL
customer_segmentation-0.0.1.dist-info/METADATA
customer_segmentation-0.0.1.dist-info/RECORD
