Metadata-Version: 2.1
Name: customer-segmentation
Version: 0.0.1
Summary: The goal of the project is to group consumers into clusters using the elbow approach.
Home-page: https://github.com/bellamartirosyan/Customer-Segmentation-for-for-Mall
License: MIT
Author: Bella Martirosyan
Author-email: bella.martirosyan2001@gmail.com
Requires-Python: >=3.10,<4.0
Classifier: License :: OSI Approved :: MIT License
Classifier: Programming Language :: Python :: 3
Classifier: Programming Language :: Python :: 3.10
Project-URL: Repository, https://github.com/bellamartirosyan/Customer-Segmentation-for-for-Mall
